mongoengine_dsl/__init__.py
mongoengine_dsl/errors.py
mongoengine_dsl/lexer/MongoEngineDSL.g4
mongoengine_dsl/lexer/MongoEngineDSL.interp
mongoengine_dsl/lexer/MongoEngineDSL.tokens
mongoengine_dsl/lexer/MongoEngineDSLLexer.interp
mongoengine_dsl/lexer/MongoEngineDSLLexer.py
mongoengine_dsl/lexer/MongoEngineDSLLexer.tokens
mongoengine_dsl/lexer/MongoEngineDSLListener.py
mongoengine_dsl/lexer/MongoEngineDSLParser.py
mongoengine_dsl/lexer/__init__.py
mongoengine_dsl/listener.py
mongoengine_dsl/mongoengine_dsl.py
mongoengine_dsl/utils.py
mongoengine_dsl-0.1.5.dist-info/LICENSE
mongoengine_dsl-0.1.5.dist-info/WHEEL
mongoengine_dsl-0.1.5.dist-info/METADATA
mongoengine_dsl-0.1.5.dist-info/RECORD
